LICENSE
MANIFEST.in
README.rst
setup.cfg
setup.py
allauth_bootstrap4/__init__.py
allauth_bootstrap4/__pycache__/__init__.cpython-35.pyc
allauth_bootstrap4/static/accounts/allauth-bootstrap4.css
allauth_bootstrap4/templates/account/account_inactive.html
allauth_bootstrap4/templates/account/base.html
allauth_bootstrap4/templates/account/email.html
allauth_bootstrap4/templates/account/email_confirm.html
allauth_bootstrap4/templates/account/layout_card.html
allauth_bootstrap4/templates/account/login.html
allauth_bootstrap4/templates/account/logout.html
allauth_bootstrap4/templates/account/password_change.html
allauth_bootstrap4/templates/account/password_reset.html
allauth_bootstrap4/templates/account/password_reset_done.html
allauth_bootstrap4/templates/account/password_reset_from_key.html
allauth_bootstrap4/templates/account/password_reset_from_key_done.html
allauth_bootstrap4/templates/account/password_set.html
allauth_bootstrap4/templates/account/signup.html
allauth_bootstrap4/templates/account/signup_closed.html
allauth_bootstrap4/templates/account/verification_sent.html
allauth_bootstrap4/templates/account/verified_email_required.html
allauth_bootstrap4/templates/account/email/email_confirmation_message.txt
allauth_bootstrap4/templates/account/email/email_confirmation_signup_message.txt
allauth_bootstrap4/templates/account/email/email_confirmation_signup_subject.txt
allauth_bootstrap4/templates/account/email/email_confirmation_subject.txt
allauth_bootstrap4/templates/account/email/password_reset_key_message.txt
allauth_bootstrap4/templates/account/email/password_reset_key_subject.txt
allauth_bootstrap4/templates/account/messages/cannot_delete_primary_email.txt
allauth_bootstrap4/templates/account/messages/email_confirmation_sent.txt
allauth_bootstrap4/templates/account/messages/email_confirmed.txt
allauth_bootstrap4/templates/account/messages/email_deleted.txt
allauth_bootstrap4/templates/account/messages/logged_in.txt
django_allauth_templates_bootstrap4.egg-info/PKG-INFO
django_allauth_templates_bootstrap4.egg-info/SOURCES.txt
django_allauth_templates_bootstrap4.egg-info/dependency_links.txt
django_allauth_templates_bootstrap4.egg-info/requires.txt
django_allauth_templates_bootstrap4.egg-info/top_level.txt