Metadata-Version: 1.1
Name: django-allauth-templates-bootstrap4
Version: 0.34.12
Summary: Bootstrap4 template pack for django-allauth
Home-page: http://github.com/tiberiuana/django-allauth-templates-bootstrap4
Author: Tiberiu Ana
Author-email: tiberiu@tiberiuana.com
License: MIT
Keywords: django auth account social openid twitter facebook oauth registration
Platform: UNKNOWN
Classifier: Development Status :: 4 - Beta
Classifier: Intended Audience :: Developers
Classifier: Topic :: Software Development :: Libraries :: Python Modules
Classifier: Environment :: Web Environment
Classifier: Topic :: Internet
Classifier: License :: OSI Approved :: MIT License
Classifier: Operating System :: OS Independent
Classifier: Programming Language :: Python
Classifier: Programming Language :: Python :: 2.7
Classifier: Programming Language :: Python :: 3.4
Classifier: Programming Language :: Python :: 3.5
Classifier: Programming Language :: Python :: 3.6
Classifier: Framework :: Django
Classifier: Framework :: Django :: 1.11
Classifier: Framework :: Django :: 2.0
